{
  "DUSK": {
    "oi": 877840.2,
    "timestamp": "2026-03-25T20:45:41.616Z"
  },
  "HYUNDAI": {
    "oi": 0.030191,
    "timestamp": "2026-03-25T20:45:41.617Z"
  },
  "USDCHF": {
    "oi": 392190.7,
    "timestamp": "2026-03-25T20:45:41.617Z"
  },
  "BMNR": {
    "oi": 4969.727,
    "timestamp": "2026-03-25T20:45:41.617Z"
  },
  "XPD": {
    "oi": 180.29259,
    "timestamp": "2026-03-25T20:45:41.617Z"
  },
  "BRENTOIL": {
    "oi": 3718.5335,
    "timestamp": "2026-03-25T20:45:41.617Z"
  },
  "ETH": {
    "oi": 35166.136,
    "timestamp": "2026-03-25T20:45:41.617Z"
  },
  "XPL": {
    "oi": 9797080.3,
    "timestamp": "2026-03-25T20:45:41.617Z"
  },
  "USDCAD": {
    "oi": 54718.5,
    "timestamp": "2026-03-25T20:45:41.618Z"
  },
  "NVDA": {
    "oi": 3216.026,
    "timestamp": "2026-03-25T20:45:41.618Z"
  },
  "KAITO": {
    "oi": 796310.2,
    "timestamp": "2026-03-25T20:45:41.618Z"
  },
  "SNDK": {
    "oi": 213.9288,
    "timestamp": "2026-03-25T20:45:41.618Z"
  },
  "WLFI": {
    "oi": 20459289.9,
    "timestamp": "2026-03-25T20:45:41.618Z"
  },
  "COIN": {
    "oi": 608.67,
    "timestamp": "2026-03-25T20:45:41.619Z"
  },
  "AVAX": {
    "oi": 130942.14,
    "timestamp": "2026-03-25T20:45:41.619Z"
  },
  "ONDO": {
    "oi": 1492016,
    "timestamp": "2026-03-25T20:45:41.619Z"
  },
  "GOOGL": {
    "oi": 1349.2832,
    "timestamp": "2026-03-25T20:45:41.619Z"
  },
  "DOT": {
    "oi": 476822.9,
    "timestamp": "2026-03-25T20:45:41.619Z"
  },
  "MON": {
    "oi": 29362403.8,
    "timestamp": "2026-03-25T20:45:41.619Z"
  },
  "ARC": {
    "oi": 2480973,
    "timestamp": "2026-03-25T20:45:41.619Z"
  },
  "PIPPIN": {
    "oi": 2918888.9,
    "timestamp": "2026-03-25T20:45:41.619Z"
  },
  "AAVE": {
    "oi": 38922.055,
    "timestamp": "2026-03-25T20:45:41.619Z"
  },
  "KRCOMP": {
    "oi": 15.67303,
    "timestamp": "2026-03-25T20:45:41.619Z"
  },
  "ROBO": {
    "oi": 3206200,
    "timestamp": "2026-03-25T20:45:41.619Z"
  },
  "1000BONK": {
    "oi": 33463705,
    "timestamp": "2026-03-25T20:45:41.619Z"
  },
  "PENGU": {
    "oi": 52648526,
    "timestamp": "2026-03-25T20:45:41.619Z"
  },
  "MSTR": {
    "oi": 1022.0674,
    "timestamp": "2026-03-25T20:45:41.619Z"
  },
  "BNB": {
    "oi": 5283.45,
    "timestamp": "2026-03-25T20:45:41.619Z"
  },
  "ZEC": {
    "oi": 8434.341,
    "timestamp": "2026-03-25T20:45:41.619Z"
  },
  "HOOD": {
    "oi": 1655.45,
    "timestamp": "2026-03-25T20:45:41.619Z"
  },
  "YZY": {
    "oi": 218146.5,
    "timestamp": "2026-03-25T20:45:41.619Z"
  },
  "STABLE": {
    "oi": 23455434,
    "timestamp": "2026-03-25T20:45:41.619Z"
  },
  "SOL": {
    "oi": 147928.632,
    "timestamp": "2026-03-25T20:45:41.619Z"
  },
  "EURUSD": {
    "oi": 1652387.3,
    "timestamp": "2026-03-25T20:45:41.619Z"
  },
  "WLD": {
    "oi": 2055458.6,
    "timestamp": "2026-03-25T20:45:41.619Z"
  },
  "LINK": {
    "oi": 132540.9,
    "timestamp": "2026-03-25T20:45:41.619Z"
  },
  "ARB": {
    "oi": 2893247.9,
    "timestamp": "2026-03-25T20:45:41.619Z"
  },
  "INTC": {
    "oi": 2346.419,
    "timestamp": "2026-03-25T20:45:41.619Z"
  },
  "GBPUSD": {
    "oi": 214886.1,
    "timestamp": "2026-03-25T20:45:41.619Z"
  },
  "LIT": {
    "oi": 31512606.23,
    "timestamp": "2026-03-25T20:45:41.619Z"
  },
  "TIA": {
    "oi": 495414.4,
    "timestamp": "2026-03-25T20:45:41.619Z"
  },
  "SKHYNIX": {
    "oi": 0.510495,
    "timestamp": "2026-03-25T20:45:41.620Z"
  },
  "MSFT": {
    "oi": 667.3952,
    "timestamp": "2026-03-25T20:45:41.620Z"
  },
  "PAXG": {
    "oi": 605.705,
    "timestamp": "2026-03-25T20:45:41.620Z"
  },
  "APT": {
    "oi": 586110.27,
    "timestamp": "2026-03-25T20:45:41.620Z"
  },
  "FARTCOIN": {
    "oi": 2803371.5,
    "timestamp": "2026-03-25T20:45:41.620Z"
  },
  "XCU": {
    "oi": 143577.07,
    "timestamp": "2026-03-25T20:45:41.620Z"
  },
  "XRP": {
    "oi": 1461217,
    "timestamp": "2026-03-25T20:45:41.620Z"
  },
  "TRUMP": {
    "oi": 152228.74,
    "timestamp": "2026-03-25T20:45:41.620Z"
  },
  "AUDUSD": {
    "oi": 35204.4,
    "timestamp": "2026-03-25T20:45:41.620Z"
  },
  "USDJPY": {
    "oi": 2009.177,
    "timestamp": "2026-03-25T20:45:41.620Z"
  },
  "TSLA": {
    "oi": 1228.2059,
    "timestamp": "2026-03-25T20:45:41.620Z"
  },
  "AAPL": {
    "oi": 674.091,
    "timestamp": "2026-03-25T20:45:41.620Z"
  },
  "SUI": {
    "oi": 678466,
    "timestamp": "2026-03-25T20:45:41.620Z"
  },
  "USELESS": {
    "oi": 20230848.3,
    "timestamp": "2026-03-25T20:45:41.621Z"
  },
  "PLTR": {
    "oi": 365.914,
    "timestamp": "2026-03-25T20:45:41.621Z"
  },
  "WIF": {
    "oi": 2150084.3,
    "timestamp": "2026-03-25T20:45:41.621Z"
  },
  "DOGE": {
    "oi": 10579296,
    "timestamp": "2026-03-25T20:45:41.621Z"
  },
  "CRCL": {
    "oi": 6906.29,
    "timestamp": "2026-03-25T20:45:41.621Z"
  },
  "QQQ": {
    "oi": 1070.9165,
    "timestamp": "2026-03-25T20:45:41.621Z"
  },
  "HANMI": {
    "oi": 0.104859,
    "timestamp": "2026-03-25T20:45:41.621Z"
  },
  "PUMP": {
    "oi": 753884875,
    "timestamp": "2026-03-25T20:45:41.621Z"
  },
  "META": {
    "oi": 517.7236,
    "timestamp": "2026-03-25T20:45:41.621Z"
  },
  "XAG": {
    "oi": 74318.6,
    "timestamp": "2026-03-25T20:45:41.621Z"
  },
  "URA": {
    "oi": 1323.077,
    "timestamp": "2026-03-25T20:45:41.621Z"
  },
  "XLM": {
    "oi": 2886223.4,
    "timestamp": "2026-03-25T20:45:41.621Z"
  },
  "JTO": {
    "oi": 467609.2,
    "timestamp": "2026-03-25T20:45:41.621Z"
  },
  "1000PEPE": {
    "oi": 307814028,
    "timestamp": "2026-03-25T20:45:41.621Z"
  },
  "IWM": {
    "oi": 34.3529,
    "timestamp": "2026-03-25T20:45:41.621Z"
  },
  "ENA": {
    "oi": 15191079.3,
    "timestamp": "2026-03-25T20:45:41.621Z"
  },
  "ASTER": {
    "oi": 3612605.8,
    "timestamp": "2026-03-25T20:45:41.621Z"
  },
  "XAU": {
    "oi": 2446.7884,
    "timestamp": "2026-03-25T20:45:41.621Z"
  },
  "SAMSUNG": {
    "oi": 0.813896,
    "timestamp": "2026-03-25T20:45:41.621Z"
  },
  "AERO": {
    "oi": 1593361.5,
    "timestamp": "2026-03-25T20:45:41.621Z"
  },
  "SKR": {
    "oi": 1496188,
    "timestamp": "2026-03-25T20:45:41.621Z"
  },
  "BTC": {
    "oi": 1478.81294,
    "timestamp": "2026-03-25T20:45:41.621Z"
  },
  "VIRTUAL": {
    "oi": 583004.1,
    "timestamp": "2026-03-25T20:45:41.621Z"
  },
  "UNI": {
    "oi": 135824.42,
    "timestamp": "2026-03-25T20:45:41.621Z"
  },
  "SPY": {
    "oi": 683.5296,
    "timestamp": "2026-03-25T20:45:41.621Z"
  },
  "DYDX": {
    "oi": 2820548,
    "timestamp": "2026-03-25T20:45:41.621Z"
  },
  "XPT": {
    "oi": 347.81776,
    "timestamp": "2026-03-25T20:45:41.621Z"
  },
  "NEAR": {
    "oi": 390012.4,
    "timestamp": "2026-03-25T20:45:41.621Z"
  },
  "ZRO": {
    "oi": 1283085.4,
    "timestamp": "2026-03-25T20:45:41.622Z"
  },
  "AMD": {
    "oi": 26.3778,
    "timestamp": "2026-03-25T20:45:41.622Z"
  },
  "WTI": {
    "oi": 58801.751,
    "timestamp": "2026-03-25T20:45:41.622Z"
  },
  "RIVER": {
    "oi": 24639.012,
    "timestamp": "2026-03-25T20:45:41.622Z"
  },
  "2Z": {
    "oi": 1593971.2,
    "timestamp": "2026-03-25T20:45:41.622Z"
  },
  "TAO": {
    "oi": 7033.496,
    "timestamp": "2026-03-25T20:45:41.622Z"
  },
  "APEX": {
    "oi": 252153,
    "timestamp": "2026-03-25T20:45:41.622Z"
  },
  "XMR": {
    "oi": 4027.098,
    "timestamp": "2026-03-25T20:45:41.622Z"
  },
  "HYPE": {
    "oi": 604779.36,
    "timestamp": "2026-03-25T20:45:41.622Z"
  },
  "TON": {
    "oi": 482756,
    "timestamp": "2026-03-25T20:45:41.622Z"
  },
  "USDKRW": {
    "oi": 343.2859,
    "timestamp": "2026-03-25T20:45:41.622Z"
  },
  "TRX": {
    "oi": 3596739.7,
    "timestamp": "2026-03-25T20:45:41.622Z"
  },
  "VVV": {
    "oi": 110987.96,
    "timestamp": "2026-03-25T20:45:41.622Z"
  },
  "AMZN": {
    "oi": 1089.915,
    "timestamp": "2026-03-25T20:45:41.622Z"
  }
}